PyramidBuilder/PyramidBuilder.py
PyramidBuilder/__init__.py
PyramidBuilder/__main__.py
PyramidBuilder-0.0.5.dist-info/METADATA
PyramidBuilder-0.0.5.dist-info/WHEEL
PyramidBuilder-0.0.5.dist-info/top_level.txt
PyramidBuilder-0.0.5.dist-info/RECORD
