Metadata-Version: 2.1
Name: PyramidBuilder
Version: 0.0.5
Summary: Auto compiles HTML, CSS and JS into one file Pyramid App.
Home-page: https://github.com/ankitkumar-13/PyramidBuilder
Author: Ankit Kumar
Author-email: ankitkumar13122003@gmail.com
License: MIT
Platform: UNKNOWN
Classifier: License :: OSI Approved :: MIT License
Classifier: Programming Language :: Python :: 3
Requires-Dist: PySimpleGUI
Requires-Dist: beautifulsoup4
